License.txt
README.md
setup.cfg
setup.py
rssd/AAA_Common.py
rssd/FileIO.py
rssd/__init__.py
rssd/instrument.py
rssd/iqdata.py
rssd/yaVISA.py
rssd/yaVISA_GUI.py
rssd/yaVISA_socket.py
rssd.egg-info/PKG-INFO
rssd.egg-info/SOURCES.txt
rssd.egg-info/dependency_links.txt
rssd.egg-info/entry_points.txt
rssd.egg-info/not-zip-safe
rssd.egg-info/requires.txt
rssd.egg-info/top_level.txt
rssd/DSO/Common.py
rssd/DSO/Spectrum_K18.py
rssd/DSO/__init__.py
rssd/NRP/Common.py
rssd/NRP/__init__.py
rssd/NRQ/Common.py
rssd/NRQ/__init__.py
rssd/OSP/Common.py
rssd/OSP/__init__.py
rssd/OTA/ATS1000.py
rssd/OTA/ATS1800.py
rssd/OTA/Common.py
rssd/OTA/__init__.py
rssd/PNA/Common.py
rssd/PNA/__init__.py
rssd/RCT/Common.py
rssd/RCT/GPRF_Meas_IQ.py
rssd/RCT/NR5G_KM601.py
rssd/RCT/__init__.py
rssd/RSI/RSI_Firmware_Feed.py
rssd/RSI/RSI_Memory.py
rssd/RSI/__init__.py
rssd/RSI/ftp.py
rssd/RSI/time.py
rssd/VNA/Common.py
rssd/VNA/__init__.py
rssd/VSA/ADemod_K7.py
rssd/VSA/Common.py
rssd/VSA/Common_proto.py
rssd/VSA/LTE_K100.py
rssd/VSA/NR5G_K144.py
rssd/VSA/NoiseFigure_K30.py
rssd/VSA/Transient_K60.py
rssd/VSA/VSA_K70.py
rssd/VSA/VSA_Template.py
rssd/VSA/WLAN_K91.py
rssd/VSA/__init__.py
rssd/VSE/Common.py
rssd/VSE/K96.py
rssd/VSE/__init__.py
rssd/VSG/Common.py
rssd/VSG/CustomDigMod.py
rssd/VSG/Fading.py
rssd/VSG/LTE_K55.py
rssd/VSG/NR5G_K144.py
rssd/VSG/WLAN_K54.py
rssd/VSG/__init__.py
rssd/VST/Common.py
rssd/VST/LTE.py
rssd/VST/NR5G_K144.py
rssd/VST/WLAN.py
rssd/VST/__init__.py
rssd/bin/__init__.py
rssd/bin/cli.py
rssd/bus/__init__.py
rssd/bus/bus.py
rssd/bus/jaSocket.py
rssd/bus/jaVISA.py
rssd/bus/test.py
rssd/examples/5GNR_SMW_CMP_FSW_EVM.py
rssd/examples/AAA_CommandDebug.py
rssd/examples/AAA_CommandTime.py
rssd/examples/AAA_Debug.py
rssd/examples/AAA_IDN_IPArry.py
rssd/examples/AAA_Repeatability.py
rssd/examples/AAA_SCPI_to_File.py
rssd/examples/AAA_Socket_Example.py
rssd/examples/AAA_VST.py
rssd/examples/OSP_Debug.py
rssd/examples/PNA_LockPower.py
rssd/examples/SMB_SMZ_Mixer.py
rssd/examples/VSA_5GNR_EVM_ACLR_SEM.py
rssd/examples/VSA_5GNR_Save_TestMode.py
rssd/examples/VSA_ACLR_IQ_Timing.py
rssd/examples/VSA_ACLR_Methods_Timing.py
rssd/examples/VSA_ACLR_Timing.py
