Metadata-Version: 2.1
Name: rssd
Version: 2022.1.18
Summary: Rohde & Schwarz SCPI Driver
Home-page: https://github.com/mclim9/rssd
Author: Martin Lim
Author-email: martin.lim@rsa.rohde-schwarz.com
License: UNKNOWN
Keywords: Rohde Schwarz test equipment FSW FSV NRP NRQ OSP SGT SMA SMB SMBV SMW SCPI VSA VSG VST
Platform: UNKNOWN
Classifier: Development Status :: 4 - Beta
Classifier: License :: OSI Approved :: MIT License
Classifier: Intended Audience :: Developers
Classifier: Intended Audience :: Science/Research
Classifier: Operating System :: Microsoft :: Windows
Classifier: Programming Language :: Python :: 2.7
Classifier: Programming Language :: Python :: 3.6
Classifier: Programming Language :: Python :: 3.7
Classifier: Programming Language :: Python :: 3.8
Classifier: Topic :: Scientific/Engineering :: Electronic Design Automation (EDA)
Classifier: Topic :: System :: Hardware :: Hardware Drivers
License-File: License.txt
